aoctools/__init__.py
aoctools/__main__.py
aoctools/bootstrapper.py
aoctools/downloader.py
aoctools/main.py
aoctools/runner.py
aoctools-0.1.0.data/scripts/aoctools
aoctools-0.1.0.dist-info/LICENSE
aoctools-0.1.0.dist-info/METADATA
aoctools-0.1.0.dist-info/WHEEL
aoctools-0.1.0.dist-info/top_level.txt
aoctools-0.1.0.dist-info/RECORD
