Metadata-Version: 2.1
Name: aoctools
Version: 0.1.0
Summary: A CLI for working with Advent of Code (AOC) problems
Home-page: https://github.com/klittlepage/aoctools
Author: Kelly Littlepage
Author-email: kelly@klittlepage.com
License: UNKNOWN
Download-URL: https://github.com/klittlepage/aoctools/archive/0.1.0.tar.gz
Platform: UNKNOWN
Classifier: Programming Language :: Python :: 3
Classifier: License :: OSI Approved :: MIT License
Classifier: Operating System :: OS Independent
Requires-Python: >=3.7
Requires-Dist: requests (<3,>=2.25.0)
Requires-Dist: python-dotenv (>=0.15.0)
Provides-Extra: dev
Requires-Dist: pylint ; extra == 'dev'
Requires-Dist: mypy ; extra == 'dev'
Requires-Dist: autopep8 ; extra == 'dev'
Requires-Dist: pre-commit ; extra == 'dev'
Requires-Dist: wheel ; extra == 'dev'
